dawa_facade
