Metadata-Version: 1.1
Name: dawa-facade
Version: 2017.12.1b5
Summary: Python client for Danmarks Adressers Web API
Home-page: https://github.com/YnkDK/Dawa-Facade
Author: Martin Storgaard Dieu
Author-email: martin@storgaarddieu.com
License: MIT
Download-URL: https://github.com/YnkDK/Dawa-Facade/archive/2017.12.1.b5.tar.gz
Keywords: dawa,Danmarks Adressers Web API,addresses,adresser,denmark,danmark
Platform: UNKNOWN
